libscan/__init__.py
libscan/cli.py
libscan/scanner.py
libscan-1.1.dist-info/METADATA
libscan-1.1.dist-info/WHEEL
libscan-1.1.dist-info/entry_points.txt
libscan-1.1.dist-info/top_level.txt
libscan-1.1.dist-info/RECORD
