Metadata-Version: 2.2
Name: libscan
Version: 1.1
Summary: libscan: A Python dependency scanner and installer
Home-page: https://github.com/IMApurbo/libscan
Author: AKM Korishee Apurbo
Author-email: bandinvisible8@gmail.com
Classifier: Programming Language :: Python :: 3
Classifier: License :: OSI Approved :: MIT License
Classifier: Operating System :: OS Independent
Requires-Python: >=3.6
Requires-Dist: rich
Requires-Dist: click
Dynamic: author
Dynamic: author-email
Dynamic: classifier
Dynamic: description
Dynamic: description-content-type
Dynamic: home-page
Dynamic: requires-dist
Dynamic: requires-python
Dynamic: summary
